{
  "postgres": "pg_ctl",
  "sshd": "sshd\" \n\"OpenSSH",
  "sh": "cmd.exe",
  "unlink": "del",
  "cron": "Task Scheduler",
  "atrun": "schtasks",
  "syslogd": "eventvwr.exe",
  "mv": "move",
  "sudo": "runas",
  "master": "taskmgr",
  "pickup": "robocopy",
  "qmgr": "qmgr\" \n\"Task Scheduler",
  "sysctl": "systeminfo",
  "dd": "dd",
  "trivial-rewrite": "trivial-rewrite\" \n\"rewrite.exe",
  "local": "local",
  "bounce": "bounce.exe",
  "sleep": "timeout",
  "env": "set",
  "ps": "tasklist",
  "expr": "cmd.exe",
  "awk": "findstr",
  "date": "date\" \n\"date",
  "fetch": "curl",
  "dhclient": "ipconfig",
  "route": "route\" \n\"route",
  "hostname": "hostname\" \n\"hostname",
  "cat": "type",
  "rm": "del",
  "mkdir": "md",
  "devd": "devmgmt.msc",
  "bash": "cmd.exe",
  "fortune": "fortune\" \n\"fortune.exe",
  "grep": "findstr",
  "ls": "dir",
  "ifconfig": "ipconfig",
  "netstat": "netstat",
  "w": "w",
  "newsyslog": "EventLog",
  "smtpd": "smtpd\" \n\"smtpd.exe",
  "nginx": "IIS",
  "php-fpm": "php-cgi",
  "anvil": "anvil.exe",
  "proxymap": "netsh",
  "df": "df\" \n\"fsutil volume diskfree",
  "find": "findstr",
  "diff": "fc",
  "sort": "sort",
  "gzip": "compress.exe",
  "uname": "systeminfo",
  "gunzip": "gzip.exe",
  "bzip2": "bzip2\" \n\"bzip2.exe",
  "adjkerntz": "chkdsk",
  "cp": "copy",
  "lockf": "LockFile",
  "mktemp": "mktemp\" \n\"mktemp",
  "mail": "outlook.exe",
  "tee": "tee",
  "wc": "wc\" \n\"findstr",
  "msgs": "msg",
  "mailwrapper": "mail",
  "cmp": "fc",
  "chkgrp": "chkgrp\" \n\"net localgroup",
  "uptime": "systeminfo",
  "sendmail": "powershell.exe",
  "postqueue": "postqueue.exe",
  "egrep": "findstr",
  "showq": "tasklist",
  "mount": "diskpart",
  "ipfw": "Windows Firewall",
  "nawk": "awk",
  "pfctl": "Windows Firewall",
  "pkg": "pkg\" \n\"winget",
  "sed": "sed.exe",
  "bzcat": "zcat",
  "uniq": "sort",
  "postdrop": "postdrop\" \n\"postdrop.exe",
  "cleanup": "del",
  "jot": "notepad.exe",
  "xz": "7z.exe",
  "fcgiwrap": "fcgiwrap.exe",
  "python2.7": "python.exe",
  "top": "Task Manager",
  "ipfstat": "netsh",
  "touch": "copy",
  "stat": "stat\" \n\"dir",
  "su": "runas.exe",
  "kldstat": "driverquery",
  "kldload": "modload",
  "kldunload": "devcon",
  "procstat": "tasklist",
  "wget": "curl",
  "dmesg": "Event Viewer",
  "chown": "icacls",
  "chmod": "icacls",
  "nice": "start",
  "csh": "cmd.exe",
  "id": "tasklist",
  "lsvfs": "fsutil",
  "tail": "tail\" \n\"tail",
  "cut": "cut.exe",
  "locate.code": "where.exe",
  "locate": "dir",
  "locate.bigram": "locate.bigram\"\n\"findstr.exe",
  "head": "more",
  "makewhatis": "makewhatis\" \n\"makedb.exe",
  "py": "python.exe"
}